[
  {
    "name": "Goblin",
    "size": "Small",
    "armor_class": 15,
    "hit_points": 7,
    "hit_dice": "2d6",
    "abilities": {
      "strength": 8,
      "dexterity": 14,
      "constitution": 10,
      "intelligence": 10,
      "wisdom": 8,
      "charisma": 8
    },
    "skills": {
      "Stealth": 6
    },
    "challenge_rating": 0.25,
    "xp": 50,
    "actions": [
      {
        "name": "Scimitar",
        "description": "Melee",
        "attack_bonus": 4,
        "damage_dice": "1d6",
        "damage_bonus": 2,
        "damage_type": "slashing",
        "range": 5,
        "action_type": "action",
        "is_multiattack": false,
        "multiattack_count": 1,
        "multiattack_targets": [],
        "reach": 5,
        "applies_condition": "",
        "condition_save": "",
        "condition_dc": 0,
        "aoe_radius": 0,
        "aoe_shape": "",
        "properties": [],
        "long_range": 0
      },
      {
        "name": "Shortbow",
        "description": "Ranged",
        "attack_bonus": 4,
        "damage_dice": "1d6",
        "damage_bonus": 2,
        "damage_type": "piercing",
        "range": 80,
        "action_type": "action",
        "is_multiattack": false,
        "multiattack_count": 1,
        "multiattack_targets": [],
        "reach": 5,
        "applies_condition": "",
        "condition_save": "",
        "condition_dc": 0,
        "aoe_radius": 0,
        "aoe_shape": "",
        "properties": [],
        "long_range": 0
      }
    ],
    "features": [
      {
        "name": "Nimble Escape",
        "description": "Disengage or Hide as bonus action",
        "feature_type": "passive",
        "uses_per_day": -1,
        "legendary_cost": 1,
        "recharge": "",
        "aura_radius": 0,
        "save_dc": 0,
        "save_ability": "",
        "applies_condition": "",
        "damage_dice": "",
        "damage_type": "",
        "mechanic": "",
        "mechanic_value": "",
        "short_rest_recharge": false,
        "phase_trigger_hp_pct": 0.0,
        "phase_description": ""
      }
    ]
  },
  {
    "name": "Skeleton",
    "creature_type": "Undead",
    "armor_class": 13,
    "hit_points": 13,
    "hit_dice": "2d8+4",
    "abilities": {
      "strength": 10,
      "dexterity": 14,
      "constitution": 15,
      "intelligence": 6,
      "wisdom": 8,
      "charisma": 5
    },
    "damage_immunities": [
      "poison"
    ],
    "damage_vulnerabilities": [
      "bludgeoning"
    ],
    "condition_immunities": [
      "Exhaustion",
      "Poisoned"
    ],
    "challenge_rating": 0.25,
    "xp": 50,
    "actions": [
      {
        "name": "Shortsword",
        "description": "Melee",
        "attack_bonus": 4,
        "damage_dice": "1d6",
        "damage_bonus": 2,
        "damage_type": "piercing",
        "range": 5,
        "action_type": "action",
        "is_multiattack": false,
        "multiattack_count": 1,
        "multiattack_targets": [],
        "reach": 5,
        "applies_condition": "",
        "condition_save": "",
        "condition_dc": 0,
        "aoe_radius": 0,
        "aoe_shape": "",
        "properties": [],
        "long_range": 0
      },
      {
        "name": "Shortbow",
        "description": "Ranged",
        "attack_bonus": 4,
        "damage_dice": "1d6",
        "damage_bonus": 2,
        "damage_type": "piercing",
        "range": 80,
        "action_type": "action",
        "is_multiattack": false,
        "multiattack_count": 1,
        "multiattack_targets": [],
        "reach": 5,
        "applies_condition": "",
        "condition_save": "",
        "condition_dc": 0,
        "aoe_radius": 0,
        "aoe_shape": "",
        "properties": [],
        "long_range": 0
      }
    ]
  },
  {
    "name": "Zombie",
    "creature_type": "Undead",
    "armor_class": 8,
    "hit_points": 22,
    "hit_dice": "3d8+9",
    "speed": 20,
    "abilities": {
      "strength": 13,
      "dexterity": 6,
      "constitution": 16,
      "intelligence": 3,
      "wisdom": 6,
      "charisma": 5
    },
    "saving_throws": {
      "Wisdom": 0
    },
    "damage_immunities": [
      "poison"
    ],
    "condition_immunities": [
      "Poisoned"
    ],
    "challenge_rating": 0.25,
    "xp": 50,
    "actions": [
      {
        "name": "Slam",
        "description": "Melee",
        "attack_bonus": 3,
        "damage_dice": "1d6",
        "damage_bonus": 1,
        "damage_type": "bludgeoning",
        "range": 5,
        "action_type": "action",
        "is_multiattack": false,
        "multiattack_count": 1,
        "multiattack_targets": [],
        "reach": 5,
        "applies_condition": "",
        "condition_save": "",
        "condition_dc": 0,
        "aoe_radius": 0,
        "aoe_shape": "",
        "properties": [],
        "long_range": 0
      }
    ],
    "features": [
      {
        "name": "Undead Fortitude",
        "description": "DC 5+dmg CON save or drop to 1 HP instead of 0",
        "feature_type": "passive",
        "uses_per_day": -1,
        "legendary_cost": 1,
        "recharge": "",
        "aura_radius": 0,
        "save_dc": 0,
        "save_ability": "",
        "applies_condition": "",
        "damage_dice": "",
        "damage_type": "",
        "mechanic": "",
        "mechanic_value": "",
        "short_rest_recharge": false,
        "phase_trigger_hp_pct": 0.0,
        "phase_description": ""
      }
    ]
  },
  {
    "name": "Wolf",
    "creature_type": "Beast",
    "armor_class": 13,
    "hit_points": 11,
    "hit_dice": "2d8+2",
    "speed": 40,
    "abilities": {
      "strength": 12,
      "dexterity": 15,
      "constitution": 12,
      "intelligence": 3,
      "wisdom": 12,
      "charisma": 6
    },
    "skills": {
      "Perception": 3,
      "Stealth": 4
    },
    "challenge_rating": 0.25,
    "xp": 50,
    "actions": [
      {
        "name": "Bite",
        "description": "Melee",
        "attack_bonus": 4,
        "damage_dice": "2d4",
        "damage_bonus": 2,
        "damage_type": "piercing",
        "range": 5,
        "action_type": "action",
        "is_multiattack": false,
        "multiattack_count": 1,
        "multiattack_targets": [],
        "reach": 5,
        "applies_condition": "Prone",
        "condition_save": "Strength",
        "condition_dc": 11,
        "aoe_radius": 0,
        "aoe_shape": "",
        "properties": [],
        "long_range": 0
      }
    ],
    "features": [
      {
        "name": "Pack Tactics",
        "description": "Adv on attack when ally adjacent to target",
        "feature_type": "passive",
        "uses_per_day": -1,
        "legendary_cost": 1,
        "recharge": "",
        "aura_radius": 0,
        "save_dc": 0,
        "save_ability": "",
        "applies_condition": "",
        "damage_dice": "",
        "damage_type": "",
        "mechanic": "",
        "mechanic_value": "",
        "short_rest_recharge": false,
        "phase_trigger_hp_pct": 0.0,
        "phase_description": ""
      }
    ]
  },
  {
    "name": "Mud Mephit",
    "size": "Small",
    "creature_type": "Elemental",
    "native_plane": "Elemental Plane",
    "armor_class": 11,
    "hit_points": 27,
    "hit_dice": "6d6+6",
    "speed": 20,
    "fly_speed": 20,
    "swim_speed": 20,
    "abilities": {
      "strength": 8,
      "dexterity": 12,
      "constitution": 12,
      "intelligence": 9,
      "wisdom": 11,
      "charisma": 7
    },
    "damage_immunities": [
      "poison",
      "acid"
    ],
    "condition_immunities": [
      "Poisoned"
    ],
    "challenge_rating": 0.25,
    "xp": 50,
    "actions": [
      {
        "name": "Fists",
        "description": "Melee",
        "attack_bonus": 3,
        "damage_dice": "1d6+1",
        "damage_bonus": "bludgeoning",
        "damage_type": "bludgeoning",
        "range": 5,
        "action_type": "action",
        "is_multiattack": false,
        "multiattack_count": 1,
        "multiattack_targets": [],
        "reach": 5,
        "applies_condition": "",
        "condition_save": "",
        "condition_dc": 0,
        "aoe_radius": 0,
        "aoe_shape": "",
        "properties": [],
        "long_range": 0
      }
    ]
  },
  {
    "name": "Giant Rat",
    "size": "Small",
    "creature_type": "Beast",
    "armor_class": 12,
    "hit_points": 7,
    "hit_dice": "2d6",
    "abilities": {
      "strength": 7,
      "dexterity": 15,
      "constitution": 11,
      "intelligence": 2,
      "wisdom": 10,
      "charisma": 4
    },
    "senses": "darkvision 60 ft.",
    "challenge_rating": 0.25,
    "xp": 50,
    "actions": [
      {
        "name": "Bite",
        "description": "Melee",
        "attack_bonus": 4,
        "damage_dice": "1d4",
        "damage_bonus": 2,
        "damage_type": "piercing",
        "range": 5,
        "action_type": "action",
        "is_multiattack": false,
        "multiattack_count": 1,
        "multiattack_targets": [],
        "reach": 5,
        "applies_condition": "",
        "condition_save": "",
        "condition_dc": 0,
        "aoe_radius": 0,
        "aoe_shape": "",
        "properties": [],
        "long_range": 0
      }
    ],
    "features": [
      {
        "name": "Pack Tactics",
        "description": "Adv on attack when ally adjacent to target",
        "feature_type": "passive",
        "uses_per_day": -1,
        "legendary_cost": 1,
        "recharge": "",
        "aura_radius": 0,
        "save_dc": 0,
        "save_ability": "",
        "applies_condition": "",
        "damage_dice": "",
        "damage_type": "",
        "mechanic": "",
        "mechanic_value": "",
        "short_rest_recharge": false,
        "phase_trigger_hp_pct": 0.0,
        "phase_description": ""
      },
      {
        "name": "Keen Smell",
        "description": "Adv on Perception checks that rely on smell",
        "feature_type": "passive",
        "uses_per_day": -1,
        "legendary_cost": 1,
        "recharge": "",
        "aura_radius": 0,
        "save_dc": 0,
        "save_ability": "",
        "applies_condition": "",
        "damage_dice": "",
        "damage_type": "",
        "mechanic": "",
        "mechanic_value": "",
        "short_rest_recharge": false,
        "phase_trigger_hp_pct": 0.0,
        "phase_description": ""
      }
    ]
  },
  {
    "name": "Pseudodragon",
    "size": "Tiny",
    "creature_type": "Dragon",
    "armor_class": 13,
    "hit_points": 7,
    "hit_dice": "2d4+2",
    "speed": 15,
    "fly_speed": 60,
    "abilities": {
      "strength": 6,
      "dexterity": 15,
      "constitution": 13,
      "intelligence": 10,
      "wisdom": 12,
      "charisma": 10
    },
    "skills": {
      "Perception": 3,
      "Stealth": 4
    },
    "condition_immunities": [
      "Poisoned"
    ],
    "senses": "blindsight 10 ft., darkvision 60 ft.",
    "challenge_rating": 0.25,
    "xp": 50,
    "actions": [
      {
        "name": "Bite",
        "description": "Melee",
        "attack_bonus": 4,
        "damage_dice": "1d4",
        "damage_bonus": 2,
        "damage_type": "piercing",
        "range": 5,
        "action_type": "action",
        "is_multiattack": false,
        "multiattack_count": 1,
        "multiattack_targets": [],
        "reach": 5,
        "applies_condition": "",
        "condition_save": "",
        "condition_dc": 0,
        "aoe_radius": 0,
        "aoe_shape": "",
        "properties": [],
        "long_range": 0
      },
      {
        "name": "Sting",
        "description": "Melee",
        "attack_bonus": 4,
        "damage_dice": "1d4",
        "damage_bonus": 2,
        "damage_type": "piercing",
        "range": 5,
        "action_type": "action",
        "is_multiattack": false,
        "multiattack_count": 1,
        "multiattack_targets": [],
        "reach": 5,
        "applies_condition": "Poisoned",
        "condition_save": "Constitution",
        "condition_dc": 11,
        "aoe_radius": 0,
        "aoe_shape": "",
        "properties": [],
        "long_range": 0
      }
    ],
    "features": [
      {
        "name": "Keen Senses",
        "description": "Adv on Perception checks that rely on sight, hearing, or smell",
        "feature_type": "passive",
        "uses_per_day": -1,
        "legendary_cost": 1,
        "recharge": "",
        "aura_radius": 0,
        "save_dc": 0,
        "save_ability": "",
        "applies_condition": "",
        "damage_dice": "",
        "damage_type": "",
        "mechanic": "",
        "mechanic_value": "",
        "short_rest_recharge": false,
        "phase_trigger_hp_pct": 0.0,
        "phase_description": ""
      },
      {
        "name": "Magic Resistance",
        "description": "Adv on saving throws against spells and magical effects",
        "feature_type": "passive",
        "uses_per_day": -1,
        "legendary_cost": 1,
        "recharge": "",
        "aura_radius": 0,
        "save_dc": 0,
        "save_ability": "",
        "applies_condition": "",
        "damage_dice": "",
        "damage_type": "",
        "mechanic": "",
        "mechanic_value": "",
        "short_rest_recharge": false,
        "phase_trigger_hp_pct": 0.0,
        "phase_description": ""
      },
      {
        "name": "Limited Telepathy",
        "description": "Communicate simple ideas and images telepathically within 100 ft.",
        "feature_type": "passive",
        "uses_per_day": -1,
        "legendary_cost": 1,
        "recharge": "",
        "aura_radius": 0,
        "save_dc": 0,
        "save_ability": "",
        "applies_condition": "",
        "damage_dice": "",
        "damage_type": "",
        "mechanic": "",
        "mechanic_value": "",
        "short_rest_recharge": false,
        "phase_trigger_hp_pct": 0.0,
        "phase_description": ""
      }
    ]
  },
  {
    "name": "Sprite",
    "size": "Tiny",
    "creature_type": "Fey",
    "armor_class": 15,
    "hit_points": 2,
    "hit_dice": "1d4",
    "speed": 10,
    "fly_speed": 40,
    "abilities": {
      "strength": 3,
      "dexterity": 18,
      "constitution": 10,
      "intelligence": 14,
      "wisdom": 13,
      "charisma": 11
    },
    "skills": {
      "Perception": 3,
      "Stealth": 8
    },
    "senses": "darkvision 60 ft.",
    "challenge_rating": 0.25,
    "xp": 50,
    "actions": [
      {
        "name": "Longsword",
        "description": "Melee",
        "attack_bonus": 2,
        "damage_dice": "1d1",
        "damage_bonus": 0,
        "damage_type": "slashing",
        "range": 5,
        "action_type": "action",
        "is_multiattack": false,
        "multiattack_count": 1,
        "multiattack_targets": [],
        "reach": 5,
        "applies_condition": "",
        "condition_save": "",
        "condition_dc": 0,
        "aoe_radius": 0,
        "aoe_shape": "",
        "properties": [],
        "long_range": 0
      },
      {
        "name": "Shortbow",
        "description": "Ranged",
        "attack_bonus": 6,
        "damage_dice": "1d1",
        "damage_bonus": 0,
        "damage_type": "piercing",
        "range": 40,
        "action_type": "action",
        "is_multiattack": false,
        "multiattack_count": 1,
        "multiattack_targets": [],
        "reach": 5,
        "applies_condition": "Poisoned",
        "condition_save": "Constitution",
        "condition_dc": 10,
        "aoe_radius": 0,
        "aoe_shape": "",
        "properties": [],
        "long_range": 0
      }
    ],
    "features": [
      {
        "name": "Heart Sight",
        "description": "Touch a creature to magically know its emotional state and alignment",
        "feature_type": "passive",
        "uses_per_day": -1,
        "legendary_cost": 1,
        "recharge": "",
        "aura_radius": 0,
        "save_dc": 0,
        "save_ability": "",
        "applies_condition": "",
        "damage_dice": "",
        "damage_type": "",
        "mechanic": "",
        "mechanic_value": "",
        "short_rest_recharge": false,
        "phase_trigger_hp_pct": 0.0,
        "phase_description": ""
      },
      {
        "name": "Invisibility",
        "description": "Magically turn invisible until attacking, casting, or concentration ends",
        "feature_type": "passive",
        "uses_per_day": -1,
        "legendary_cost": 1,
        "recharge": "",
        "aura_radius": 0,
        "save_dc": 0,
        "save_ability": "",
        "applies_condition": "",
        "damage_dice": "",
        "damage_type": "",
        "mechanic": "",
        "mechanic_value": "",
        "short_rest_recharge": false,
        "phase_trigger_hp_pct": 0.0,
        "phase_description": ""
      }
    ]
  },
  {
    "name": "Swarm of Rats",
    "creature_type": "Swarm of Tiny Beasts",
    "hit_points": 24,
    "hit_dice": "7d8-7",
    "abilities": {
      "strength": 9,
      "dexterity": 11,
      "constitution": 9,
      "intelligence": 2,
      "wisdom": 10,
      "charisma": 3
    },
    "damage_resistances": [
      "bludgeoning",
      "piercing",
      "slashing"
    ],
    "condition_immunities": [
      "Charmed",
      "Frightened",
      "Grappled",
      "Paralyzed",
      "Petrified",
      "Prone",
      "Restrained",
      "Stunned"
    ],
    "senses": "darkvision 30 ft.",
    "challenge_rating": 0.25,
    "xp": 50,
    "actions": [
      {
        "name": "Bites",
        "description": "Melee",
        "attack_bonus": 2,
        "damage_dice": "2d6",
        "damage_bonus": 0,
        "damage_type": "piercing",
        "range": 5,
        "action_type": "action",
        "is_multiattack": false,
        "multiattack_count": 1,
        "multiattack_targets": [],
        "reach": 5,
        "applies_condition": "",
        "condition_save": "",
        "condition_dc": 0,
        "aoe_radius": 0,
        "aoe_shape": "",
        "properties": [],
        "long_range": 0
      }
    ],
    "features": [
      {
        "name": "Keen Smell",
        "description": "Adv on Perception checks that rely on smell",
        "feature_type": "passive",
        "uses_per_day": -1,
        "legendary_cost": 1,
        "recharge": "",
        "aura_radius": 0,
        "save_dc": 0,
        "save_ability": "",
        "applies_condition": "",
        "damage_dice": "",
        "damage_type": "",
        "mechanic": "",
        "mechanic_value": "",
        "short_rest_recharge": false,
        "phase_trigger_hp_pct": 0.0,
        "phase_description": ""
      },
      {
        "name": "Swarm",
        "description": "Can occupy another creature's space and vice versa; can move through any opening large enough for a Tiny creature; half damage dice when at half HP or fewer",
        "feature_type": "passive",
        "uses_per_day": -1,
        "legendary_cost": 1,
        "recharge": "",
        "aura_radius": 0,
        "save_dc": 0,
        "save_ability": "",
        "applies_condition": "",
        "damage_dice": "",
        "damage_type": "",
        "mechanic": "",
        "mechanic_value": "",
        "short_rest_recharge": false,
        "phase_trigger_hp_pct": 0.0,
        "phase_description": ""
      }
    ]
  },
  {
    "name": "Acolyte",
    "hit_points": 9,
    "hit_dice": "2d8",
    "abilities": {
      "strength": 10,
      "dexterity": 10,
      "constitution": 10,
      "intelligence": 10,
      "wisdom": 14,
      "charisma": 11
    },
    "skills": {
      "Medicine": 4,
      "Religion": 2
    },
    "challenge_rating": 0.25,
    "xp": 50,
    "actions": [
      {
        "name": "Club",
        "description": "Melee",
        "attack_bonus": 2,
        "damage_dice": "1d4",
        "damage_bonus": 0,
        "damage_type": "bludgeoning",
        "range": 5,
        "action_type": "action",
        "is_multiattack": false,
        "multiattack_count": 1,
        "multiattack_targets": [],
        "reach": 5,
        "applies_condition": "",
        "condition_save": "",
        "condition_dc": 0,
        "aoe_radius": 0,
        "aoe_shape": "",
        "properties": [],
        "long_range": 0
      }
    ],
    "spellcasting_ability": "Wisdom",
    "spell_save_dc": 12,
    "spell_attack_bonus": 4,
    "spell_slots": {
      "1st": 3
    },
    "features": [
      {
        "name": "Spellcasting",
        "description": "1st-level spellcaster. Spellcasting ability is Wisdom (spell save DC 12, +4 to hit). Cantrips: Light, Sacred Flame, Thaumaturgy. 1st level (3 slots): Bless, Cure Wounds, Sanctuary",
        "feature_type": "passive",
        "uses_per_day": -1,
        "legendary_cost": 1,
        "recharge": "",
        "aura_radius": 0,
        "save_dc": 0,
        "save_ability": "",
        "applies_condition": "",
        "damage_dice": "",
        "damage_type": "",
        "mechanic": "",
        "mechanic_value": "",
        "short_rest_recharge": false,
        "phase_trigger_hp_pct": 0.0,
        "phase_description": ""
      }
    ],
    "spells_known": [
      {
        "name": "Bless",
        "level": 1,
        "school": "Evocation",
        "action_type": "action",
        "range": 30,
        "aoe_radius": 0,
        "aoe_shape": "",
        "damage_dice": "",
        "damage_type": "fire",
        "damage_scaling": "",
        "save_ability": "",
        "save_dc_fixed": 0,
        "attack_bonus_fixed": 0,
        "applies_condition": "",
        "condition_on_save": false,
        "repeat_save": true,
        "heals": "",
        "targets": "aoe",
        "concentration": true,
        "duration": "1 minute",
        "description": "+1d4 to attacks/saves for 3 targets",
        "half_on_save": true,
        "ritual": false,
        "components": "",
        "summon_name": "",
        "summon_hp": 0,
        "summon_ac": 10,
        "summon_damage_dice": "",
        "summon_damage_type": "",
        "summon_attack_bonus": 0,
        "summon_duration_rounds": 10,
        "bonus_damage_dice": "",
        "bonus_damage_type": "",
        "creates_terrain": "",
        "innate": false,
        "innate_uses_per_day": -1
      },
      {
        "name": "Cure Wounds",
        "level": 1,
        "school": "Evocation",
        "action_type": "action",
        "range": 5,
        "aoe_radius": 0,
        "aoe_shape": "",
        "damage_dice": "",
        "damage_type": "fire",
        "damage_scaling": "",
        "save_ability": "",
        "save_dc_fixed": 0,
        "attack_bonus_fixed": 0,
        "applies_condition": "",
        "condition_on_save": false,
        "repeat_save": true,
        "heals": "1d8+4",
        "targets": "single",
        "concentration": false,
        "duration": "",
        "description": "Heals 1d8 + mod",
        "half_on_save": true,
        "ritual": false,
        "components": "",
        "summon_name": "",
        "summon_hp": 0,
        "summon_ac": 10,
        "summon_damage_dice": "",
        "summon_damage_type": "",
        "summon_attack_bonus": 0,
        "summon_duration_rounds": 10,
        "bonus_damage_dice": "",
        "bonus_damage_type": "",
        "creates_terrain": "",
        "innate": false,
        "innate_uses_per_day": -1
      }
    ],
    "cantrips": [
      {
        "name": "Sacred Flame",
        "level": 0,
        "school": "Evocation",
        "action_type": "action",
        "range": 60,
        "aoe_radius": 0,
        "aoe_shape": "",
        "damage_dice": "1d8",
        "damage_type": "radiant",
        "damage_scaling": "",
        "save_ability": "Dexterity",
        "save_dc_fixed": 12,
        "attack_bonus_fixed": 0,
        "applies_condition": "",
        "condition_on_save": false,
        "repeat_save": true,
        "heals": "",
        "targets": "single",
        "concentration": false,
        "duration": "",
        "description": "",
        "half_on_save": false,
        "ritual": false,
        "components": "",
        "summon_name": "",
        "summon_hp": 0,
        "summon_ac": 10,
        "summon_damage_dice": "",
        "summon_damage_type": "",
        "summon_attack_bonus": 0,
        "summon_duration_rounds": 10,
        "bonus_damage_dice": "",
        "bonus_damage_type": "",
        "creates_terrain": "",
        "innate": false,
        "innate_uses_per_day": -1
      }
    ]
  },
  {
    "name": "Blink Dog",
    "creature_type": "Fey",
    "armor_class": 13,
    "hit_points": 22,
    "hit_dice": "4d8+4",
    "speed": 40,
    "abilities": {
      "strength": 12,
      "dexterity": 17,
      "constitution": 12,
      "intelligence": 10,
      "wisdom": 13,
      "charisma": 11
    },
    "skills": {
      "Perception": 3,
      "Stealth": 5
    },
    "senses": "darkvision 60 ft.",
    "challenge_rating": 0.25,
    "xp": 50,
    "actions": [
      {
        "name": "Bite",
        "description": "Melee",
        "attack_bonus": 3,
        "damage_dice": "1d6",
        "damage_bonus": 1,
        "damage_type": "piercing",
        "range": 5,
        "action_type": "action",
        "is_multiattack": false,
        "multiattack_count": 1,
        "multiattack_targets": [],
        "reach": 5,
        "applies_condition": "",
        "condition_save": "",
        "condition_dc": 0,
        "aoe_radius": 0,
        "aoe_shape": "",
        "properties": [],
        "long_range": 0
      }
    ],
    "features": [
      {
        "name": "Keen Hearing and Smell",
        "description": "Adv on Perception checks that rely on hearing or smell",
        "feature_type": "passive",
        "uses_per_day": -1,
        "legendary_cost": 1,
        "recharge": "",
        "aura_radius": 0,
        "save_dc": 0,
        "save_ability": "",
        "applies_condition": "",
        "damage_dice": "",
        "damage_type": "",
        "mechanic": "",
        "mechanic_value": "",
        "short_rest_recharge": false,
        "phase_trigger_hp_pct": 0.0,
        "phase_description": ""
      },
      {
        "name": "Teleport",
        "description": "Bonus action to magically teleport up to 40 ft. to an unoccupied space the dog can see",
        "feature_type": "trait",
        "uses_per_day": -1,
        "legendary_cost": 1,
        "recharge": "",
        "aura_radius": 0,
        "save_dc": 0,
        "save_ability": "",
        "applies_condition": "",
        "damage_dice": "",
        "damage_type": "",
        "mechanic": "",
        "mechanic_value": "",
        "short_rest_recharge": false,
        "phase_trigger_hp_pct": 0.0,
        "phase_description": ""
      }
    ]
  },
  {
    "name": "Giant Frog",
    "creature_type": "Beast",
    "armor_class": 11,
    "hit_points": 18,
    "hit_dice": "4d8",
    "swim_speed": 30,
    "abilities": {
      "strength": 12,
      "dexterity": 13,
      "constitution": 11,
      "intelligence": 2,
      "wisdom": 10,
      "charisma": 3
    },
    "senses": "darkvision 30 ft.",
    "challenge_rating": 0.25,
    "xp": 50,
    "actions": [
      {
        "name": "Bite",
        "description": "Melee",
        "attack_bonus": 3,
        "damage_dice": "1d6",
        "damage_bonus": 1,
        "damage_type": "piercing",
        "range": 5,
        "action_type": "action",
        "is_multiattack": false,
        "multiattack_count": 1,
        "multiattack_targets": [],
        "reach": 5,
        "applies_condition": "Grappled",
        "condition_save": "Strength",
        "condition_dc": 11,
        "aoe_radius": 0,
        "aoe_shape": "",
        "properties": [],
        "long_range": 0
      }
    ],
    "features": [
      {
        "name": "Amphibious",
        "description": "Can breathe air and water",
        "feature_type": "passive",
        "uses_per_day": -1,
        "legendary_cost": 1,
        "recharge": "",
        "aura_radius": 0,
        "save_dc": 0,
        "save_ability": "",
        "applies_condition": "",
        "damage_dice": "",
        "damage_type": "",
        "mechanic": "",
        "mechanic_value": "",
        "short_rest_recharge": false,
        "phase_trigger_hp_pct": 0.0,
        "phase_description": ""
      },
      {
        "name": "Standing Leap",
        "description": "Long jump 20 ft., high jump 10 ft., with or without running start",
        "feature_type": "passive",
        "uses_per_day": -1,
        "legendary_cost": 1,
        "recharge": "",
        "aura_radius": 0,
        "save_dc": 0,
        "save_ability": "",
        "applies_condition": "",
        "damage_dice": "",
        "damage_type": "",
        "mechanic": "",
        "mechanic_value": "",
        "short_rest_recharge": false,
        "phase_trigger_hp_pct": 0.0,
        "phase_description": ""
      },
      {
        "name": "Swallow",
        "description": "If target is Small or smaller and grappled, swallowed: blinded, restrained, 2d4 acid damage per turn. Frog can only swallow one target at a time",
        "feature_type": "passive",
        "uses_per_day": -1,
        "legendary_cost": 1,
        "recharge": "",
        "aura_radius": 0,
        "save_dc": 0,
        "save_ability": "",
        "applies_condition": "",
        "damage_dice": "",
        "damage_type": "",
        "mechanic": "",
        "mechanic_value": "",
        "short_rest_recharge": false,
        "phase_trigger_hp_pct": 0.0,
        "phase_description": ""
      }
    ]
  },
  {
    "name": "Giant Poisonous Snake",
    "creature_type": "Beast",
    "armor_class": 14,
    "hit_points": 11,
    "hit_dice": "2d8+2",
    "swim_speed": 30,
    "abilities": {
      "strength": 10,
      "dexterity": 18,
      "constitution": 13,
      "intelligence": 2,
      "wisdom": 10,
      "charisma": 3
    },
    "senses": "blindsight 10 ft.",
    "challenge_rating": 0.25,
    "xp": 50,
    "actions": [
      {
        "name": "Bite",
        "description": "Melee",
        "attack_bonus": 6,
        "damage_dice": "1d4",
        "damage_bonus": 4,
        "damage_type": "piercing",
        "range": 5,
        "action_type": "action",
        "is_multiattack": false,
        "multiattack_count": 1,
        "multiattack_targets": [],
        "reach": 5,
        "applies_condition": "Poisoned",
        "condition_save": "Constitution",
        "condition_dc": 11,
        "aoe_radius": 0,
        "aoe_shape": "",
        "properties": [],
        "long_range": 0
      }
    ],
    "features": [
      {
        "name": "Venomous Bite",
        "description": "On hit, target takes additional 3d6 poison damage (DC 11 CON save for half)",
        "feature_type": "passive",
        "uses_per_day": -1,
        "legendary_cost": 1,
        "recharge": "",
        "aura_radius": 0,
        "save_dc": 0,
        "save_ability": "",
        "applies_condition": "",
        "damage_dice": "",
        "damage_type": "",
        "mechanic": "",
        "mechanic_value": "",
        "short_rest_recharge": false,
        "phase_trigger_hp_pct": 0.0,
        "phase_description": ""
      }
    ]
  }
]